{
  "tracks" : [ {
    "album" : {
      "album_type" : "album",
      "artists" : [ {
        "external_urls" : {
          "spotify" : "https://open.spotify.com/artist/6KImCVD70vtIoJWnq6nGn3"
        },
        "href" : "https://api.spotify.com/v1/artists/6KImCVD70vtIoJWnq6nGn3",
        "id" : "6KImCVD70vtIoJWnq6nGn3",
        "name" : "Harry Styles",
        "type" : "artist",
        "uri" : "spotify:artist:6KImCVD70vtIoJWnq6nGn3"
      } ],
      "external_urls" : {
        "spotify" : "https://open.spotify.com/album/7xV2TzoaVc0ycW7fwBwAml"
      },
      "href" : "https://api.spotify.com/v1/albums/7xV2TzoaVc0ycW7fwBwAml",
      "id" : "7xV2TzoaVc0ycW7fwBwAml",
      "images" : [ {
        "height" : 640,
        "url" : "https://i.scdn.co/image/ab67616d0000b27377fdcfda6535601aff081b6a",
        "width" : 640
      }, {
        "height" : 300,
        "url" : "https://i.scdn.co/image/ab67616d00001e0277fdcfda6535601aff081b6a",
        "width" : 300
      }, {
        "height" : 64,
        "url" : "https://i.scdn.co/image/ab67616d0000485177fdcfda6535601aff081b6a",
        "width" : 64
      } ],
      "name" : "Fine Line",
      "release_date" : "2019-12-13",
      "release_date_precision" : "day",
      "total_tracks" : 12,
      "type" : "album",
      "uri" : "spotify:album:7xV2TzoaVc0ycW7fwBwAml"
    },
    "artists" : [ {
      "external_urls" : {
        "spotify" : "https://open.spotify.com/artist/6KImCVD70vtIoJWnq6nGn3"
      },
      "href" : "https://api.spotify.com/v1/artists/6KImCVD70vtIoJWnq6nGn3",
      "id" : "6KImCVD70vtIoJWnq6nGn3",
      "name" : "Harry Styles",
      "type" : "artist",
      "uri" : "spotify:artist:6KImCVD70vtIoJWnq6nGn3"
    } ],
    "disc_number" : 1,
    "duration_ms" : 174000,
    "explicit" : false,
    "external_ids" : {
      "isrc" : "USSM11912587"
    },
    "external_urls" : {
      "spotify" : "https://open.spotify.com/track/6UelLqGlWMcVH1E5c4H7lY"
    },
    "href" : "https://api.spotify.com/v1/tracks/6UelLqGlWMcVH1E5c4H7lY",
    "id" : "6UelLqGlWMcVH1E5c4H7lY",
    "is_local" : false,
    "is_playable" : true,
    "name" : "Watermelon Sugar",
    "popularity" : 94,
    "preview_url" : "https://p.scdn.co/mp3-preview/0c51b5f7ed852504844feebfb4f4b7f099452662?cid=be7bf93d831d42e2b9e239d3fc1f8a8e",
    "track_number" : 2,
    "type" : "track",
    "uri" : "spotify:track:6UelLqGlWMcVH1E5c4H7lY"
  }, {
    "album" : {
      "album_type" : "album",
      "artists" : [ {
        "external_urls" : {
          "spotify" : "https://open.spotify.com/artist/6KImCVD70vtIoJWnq6nGn3"
        },
        "href" : "https://api.spotify.com/v1/artists/6KImCVD70vtIoJWnq6nGn3",
        "id" : "6KImCVD70vtIoJWnq6nGn3",
        "name" : "Harry Styles",
        "type" : "artist",
        "uri" : "spotify:artist:6KImCVD70vtIoJWnq6nGn3"
      } ],
      "external_urls" : {
        "spotify" : "https://open.spotify.com/album/7xV2TzoaVc0ycW7fwBwAml"
      },
      "href" : "https://api.spotify.com/v1/albums/7xV2TzoaVc0ycW7fwBwAml",
      "id" : "7xV2TzoaVc0ycW7fwBwAml",
      "images" : [ {
        "height" : 640,
        "url" : "https://i.scdn.co/image/ab67616d0000b27377fdcfda6535601aff081b6a",
        "width" : 640
      }, {
        "height" : 300,
        "url" : "https://i.scdn.co/image/ab67616d00001e0277fdcfda6535601aff081b6a",
        "width" : 300
      }, {
        "height" : 64,
        "url" : "https://i.scdn.co/image/ab67616d0000485177fdcfda6535601aff081b6a",
        "width" : 64
      } ],
      "name" : "Fine Line",
      "release_date" : "2019-12-13",
      "release_date_precision" : "day",
      "total_tracks" : 12,
      "type" : "album",
      "uri" : "spotify:album:7xV2TzoaVc0ycW7fwBwAml"
    },
    "artists" : [ {
      "external_urls" : {
        "spotify" : "https://open.spotify.com/artist/6KImCVD70vtIoJWnq6nGn3"
      },
      "href" : "https://api.spotify.com/v1/artists/6KImCVD70vtIoJWnq6nGn3",
      "id" : "6KImCVD70vtIoJWnq6nGn3",
      "name" : "Harry Styles",
      "type" : "artist",
      "uri" : "spotify:artist:6KImCVD70vtIoJWnq6nGn3"
    } ],
    "disc_number" : 1,
    "duration_ms" : 207133,
    "explicit" : false,
    "external_ids" : {
      "isrc" : "USSM11912588"
    },
    "external_urls" : {
      "spotify" : "https://open.spotify.com/track/3jjujdWJ72nww5eGnfs2E7"
    },
    "href" : "https://api.spotify.com/v1/tracks/3jjujdWJ72nww5eGnfs2E7",
    "id" : "3jjujdWJ72nww5eGnfs2E7",
    "is_local" : false,
    "is_playable" : true,
    "name" : "Adore You",
    "popularity" : 87,
    "preview_url" : "https://p.scdn.co/mp3-preview/2dbeaa922270b3372d221f09c773a38696aed573?cid=be7bf93d831d42e2b9e239d3fc1f8a8e",
    "track_number" : 3,
    "type" : "track",
    "uri" : "spotify:track:3jjujdWJ72nww5eGnfs2E7"
  }, {
    "album" : {
      "album_type" : "album",
      "artists" : [ {
        "external_urls" : {
          "spotify" : "https://open.spotify.com/artist/6KImCVD70vtIoJWnq6nGn3"
        },
        "href" : "https://api.spotify.com/v1/artists/6KImCVD70vtIoJWnq6nGn3",
        "id" : "6KImCVD70vtIoJWnq6nGn3",
        "name" : "Harry Styles",
        "type" : "artist",
        "uri" : "spotify:artist:6KImCVD70vtIoJWnq6nGn3"
      } ],
      "external_urls" : {
        "spotify" : "https://open.spotify.com/album/7xV2TzoaVc0ycW7fwBwAml"
      },
      "href" : "https://api.spotify.com/v1/albums/7xV2TzoaVc0ycW7fwBwAml",
      "id" : "7xV2TzoaVc0ycW7fwBwAml",
      "images" : [ {
        "height" : 640,
        "url" : "https://i.scdn.co/image/ab67616d0000b27377fdcfda6535601aff081b6a",
        "width" : 640
      }, {
        "height" : 300,
        "url" : "https://i.scdn.co/image/ab67616d00001e0277fdcfda6535601aff081b6a",
        "width" : 300
      }, {
        "height" : 64,
        "url" : "https://i.scdn.co/image/ab67616d0000485177fdcfda6535601aff081b6a",
        "width" : 64
      } ],
      "name" : "Fine Line",
      "release_date" : "2019-12-13",
      "release_date_precision" : "day",
      "total_tracks" : 12,
      "type" : "album",
      "uri" : "spotify:album:7xV2TzoaVc0ycW7fwBwAml"
    },
    "artists" : [ {
      "external_urls" : {
        "spotify" : "https://open.spotify.com/artist/6KImCVD70vtIoJWnq6nGn3"
      },
      "href" : "https://api.spotify.com/v1/artists/6KImCVD70vtIoJWnq6nGn3",
      "id" : "6KImCVD70vtIoJWnq6nGn3",
      "name" : "Harry Styles",
      "type" : "artist",
      "uri" : "spotify:artist:6KImCVD70vtIoJWnq6nGn3"
    } ],
    "disc_number" : 1,
    "duration_ms" : 240133,
    "explicit" : false,
    "external_ids" : {
      "isrc" : "USSM11912590"
    },
    "external_urls" : {
      "spotify" : "https://open.spotify.com/track/1ZMiCix7XSAbfAJlEZWMCp"
    },
    "href" : "https://api.spotify.com/v1/tracks/1ZMiCix7XSAbfAJlEZWMCp",
    "id" : "1ZMiCix7XSAbfAJlEZWMCp",
    "is_local" : false,
    "is_playable" : true,
    "name" : "Falling",
    "popularity" : 87,
    "preview_url" : "https://p.scdn.co/mp3-preview/755e88e49f038885df13efc6689381a2068e972d?cid=be7bf93d831d42e2b9e239d3fc1f8a8e",
    "track_number" : 6,
    "type" : "track",
    "uri" : "spotify:track:1ZMiCix7XSAbfAJlEZWMCp"
  }, {
    "album" : {
      "album_type" : "album",
      "artists" : [ {
        "external_urls" : {
          "spotify" : "https://open.spotify.com/artist/6KImCVD70vtIoJWnq6nGn3"
        },
        "href" : "https://api.spotify.com/v1/artists/6KImCVD70vtIoJWnq6nGn3",
        "id" : "6KImCVD70vtIoJWnq6nGn3",
        "name" : "Harry Styles",
        "type" : "artist",
        "uri" : "spotify:artist:6KImCVD70vtIoJWnq6nGn3"
      } ],
      "external_urls" : {
        "spotify" : "https://open.spotify.com/album/7xV2TzoaVc0ycW7fwBwAml"
      },
      "href" : "https://api.spotify.com/v1/albums/7xV2TzoaVc0ycW7fwBwAml",
      "id" : "7xV2TzoaVc0ycW7fwBwAml",
      "images" : [ {
        "height" : 640,
        "url" : "https://i.scdn.co/image/ab67616d0000b27377fdcfda6535601aff081b6a",
        "width" : 640
      }, {
        "height" : 300,
        "url" : "https://i.scdn.co/image/ab67616d00001e0277fdcfda6535601aff081b6a",
        "width" : 300
      }, {
        "height" : 64,
        "url" : "https://i.scdn.co/image/ab67616d0000485177fdcfda6535601aff081b6a",
        "width" : 64
      } ],
      "name" : "Fine Line",
      "release_date" : "2019-12-13",
      "release_date_precision" : "day",
      "total_tracks" : 12,
      "type" : "album",
      "uri" : "spotify:album:7xV2TzoaVc0ycW7fwBwAml"
    },
    "artists" : [ {
      "external_urls" : {
        "spotify" : "https://open.spotify.com/artist/6KImCVD70vtIoJWnq6nGn3"
      },
      "href" : "https://api.spotify.com/v1/artists/6KImCVD70vtIoJWnq6nGn3",
      "id" : "6KImCVD70vtIoJWnq6nGn3",
      "name" : "Harry Styles",
      "type" : "artist",
      "uri" : "spotify:artist:6KImCVD70vtIoJWnq6nGn3"
    } ],
    "disc_number" : 1,
    "duration_ms" : 208906,
    "explicit" : false,
    "external_ids" : {
      "isrc" : "USSM11912586"
    },
    "external_urls" : {
      "spotify" : "https://open.spotify.com/track/45S5WTQEGOB1VHr1Q4FuPl"
    },
    "href" : "https://api.spotify.com/v1/tracks/45S5WTQEGOB1VHr1Q4FuPl",
    "id" : "45S5WTQEGOB1VHr1Q4FuPl",
    "is_local" : false,
    "is_playable" : true,
    "name" : "Golden",
    "popularity" : 84,
    "preview_url" : "https://p.scdn.co/mp3-preview/b8bbc5ca9cc5fc1a9ddb73fa47107f00c59c422c?cid=be7bf93d831d42e2b9e239d3fc1f8a8e",
    "track_number" : 1,
    "type" : "track",
    "uri" : "spotify:track:45S5WTQEGOB1VHr1Q4FuPl"
  }, {
    "album" : {
      "album_type" : "album",
      "artists" : [ {
        "external_urls" : {
          "spotify" : "https://open.spotify.com/artist/6KImCVD70vtIoJWnq6nGn3"
        },
        "href" : "https://api.spotify.com/v1/artists/6KImCVD70vtIoJWnq6nGn3",
        "id" : "6KImCVD70vtIoJWnq6nGn3",
        "name" : "Harry Styles",
        "type" : "artist",
        "uri" : "spotify:artist:6KImCVD70vtIoJWnq6nGn3"
      } ],
      "external_urls" : {
        "spotify" : "https://open.spotify.com/album/1FZKIm3JVDCxTchXDo5jOV"
      },
      "href" : "https://api.spotify.com/v1/albums/1FZKIm3JVDCxTchXDo5jOV",
      "id" : "1FZKIm3JVDCxTchXDo5jOV",
      "images" : [ {
        "height" : 640,
        "url" : "https://i.scdn.co/image/ab67616d0000b2736c619c39c853f8b1d67b7859",
        "width" : 640
      }, {
        "height" : 300,
        "url" : "https://i.scdn.co/image/ab67616d00001e026c619c39c853f8b1d67b7859",
        "width" : 300
      }, {
        "height" : 64,
        "url" : "https://i.scdn.co/image/ab67616d000048516c619c39c853f8b1d67b7859",
        "width" : 64
      } ],
      "name" : "Harry Styles",
      "release_date" : "2017-05-12",
      "release_date_precision" : "day",
      "total_tracks" : 10,
      "type" : "album",
      "uri" : "spotify:album:1FZKIm3JVDCxTchXDo5jOV"
    },
    "artists" : [ {
      "external_urls" : {
        "spotify" : "https://open.spotify.com/artist/6KImCVD70vtIoJWnq6nGn3"
      },
      "href" : "https://api.spotify.com/v1/artists/6KImCVD70vtIoJWnq6nGn3",
      "id" : "6KImCVD70vtIoJWnq6nGn3",
      "name" : "Harry Styles",
      "type" : "artist",
      "uri" : "spotify:artist:6KImCVD70vtIoJWnq6nGn3"
    } ],
    "disc_number" : 1,
    "duration_ms" : 340706,
    "explicit" : false,
    "external_ids" : {
      "isrc" : "USSM11703595"
    },
    "external_urls" : {
      "spotify" : "https://open.spotify.com/track/5Ohxk2dO5COHF1krpoPigN"
    },
    "href" : "https://api.spotify.com/v1/tracks/5Ohxk2dO5COHF1krpoPigN",
    "id" : "5Ohxk2dO5COHF1krpoPigN",
    "is_local" : false,
    "is_playable" : true,
    "name" : "Sign of the Times",
    "popularity" : 82,
    "preview_url" : "https://p.scdn.co/mp3-preview/af237206f611b722f48620ece049aff3b8650e77?cid=be7bf93d831d42e2b9e239d3fc1f8a8e",
    "track_number" : 2,
    "type" : "track",
    "uri" : "spotify:track:5Ohxk2dO5COHF1krpoPigN"
  }, {
    "album" : {
      "album_type" : "album",
      "artists" : [ {
        "external_urls" : {
          "spotify" : "https://open.spotify.com/artist/6KImCVD70vtIoJWnq6nGn3"
        },
        "href" : "https://api.spotify.com/v1/artists/6KImCVD70vtIoJWnq6nGn3",
        "id" : "6KImCVD70vtIoJWnq6nGn3",
        "name" : "Harry Styles",
        "type" : "artist",
        "uri" : "spotify:artist:6KImCVD70vtIoJWnq6nGn3"
      } ],
      "external_urls" : {
        "spotify" : "https://open.spotify.com/album/7xV2TzoaVc0ycW7fwBwAml"
      },
      "href" : "https://api.spotify.com/v1/albums/7xV2TzoaVc0ycW7fwBwAml",
      "id" : "7xV2TzoaVc0ycW7fwBwAml",
      "images" : [ {
        "height" : 640,
        "url" : "https://i.scdn.co/image/ab67616d0000b27377fdcfda6535601aff081b6a",
        "width" : 640
      }, {
        "height" : 300,
        "url" : "https://i.scdn.co/image/ab67616d00001e0277fdcfda6535601aff081b6a",
        "width" : 300
      }, {
        "height" : 64,
        "url" : "https://i.scdn.co/image/ab67616d0000485177fdcfda6535601aff081b6a",
        "width" : 64
      } ],
      "name" : "Fine Line",
      "release_date" : "2019-12-13",
      "release_date_precision" : "day",
      "total_tracks" : 12,
      "type" : "album",
      "uri" : "spotify:album:7xV2TzoaVc0ycW7fwBwAml"
    },
    "artists" : [ {
      "external_urls" : {
        "spotify" : "https://open.spotify.com/artist/6KImCVD70vtIoJWnq6nGn3"
      },
      "href" : "https://api.spotify.com/v1/artists/6KImCVD70vtIoJWnq6nGn3",
      "id" : "6KImCVD70vtIoJWnq6nGn3",
      "name" : "Harry Styles",
      "type" : "artist",
      "uri" : "spotify:artist:6KImCVD70vtIoJWnq6nGn3"
    } ],
    "disc_number" : 1,
    "duration_ms" : 172213,
    "explicit" : false,
    "external_ids" : {
      "isrc" : "USSM11910404"
    },
    "external_urls" : {
      "spotify" : "https://open.spotify.com/track/4jAIqgrPjKLTY9Gbez25Qb"
    },
    "href" : "https://api.spotify.com/v1/tracks/4jAIqgrPjKLTY9Gbez25Qb",
    "id" : "4jAIqgrPjKLTY9Gbez25Qb",
    "is_local" : false,
    "is_playable" : true,
    "name" : "Lights Up",
    "popularity" : 82,
    "preview_url" : "https://p.scdn.co/mp3-preview/2a91b13bd532e2752e0c48d23a459b873d9bf530?cid=be7bf93d831d42e2b9e239d3fc1f8a8e",
    "track_number" : 4,
    "type" : "track",
    "uri" : "spotify:track:4jAIqgrPjKLTY9Gbez25Qb"
  }, {
    "album" : {
      "album_type" : "album",
      "artists" : [ {
        "external_urls" : {
          "spotify" : "https://open.spotify.com/artist/6KImCVD70vtIoJWnq6nGn3"
        },
        "href" : "https://api.spotify.com/v1/artists/6KImCVD70vtIoJWnq6nGn3",
        "id" : "6KImCVD70vtIoJWnq6nGn3",
        "name" : "Harry Styles",
        "type" : "artist",
        "uri" : "spotify:artist:6KImCVD70vtIoJWnq6nGn3"
      } ],
      "external_urls" : {
        "spotify" : "https://open.spotify.com/album/1FZKIm3JVDCxTchXDo5jOV"
      },
      "href" : "https://api.spotify.com/v1/albums/1FZKIm3JVDCxTchXDo5jOV",
      "id" : "1FZKIm3JVDCxTchXDo5jOV",
      "images" : [ {
        "height" : 640,
        "url" : "https://i.scdn.co/image/ab67616d0000b2736c619c39c853f8b1d67b7859",
        "width" : 640
      }, {
        "height" : 300,
        "url" : "https://i.scdn.co/image/ab67616d00001e026c619c39c853f8b1d67b7859",
        "width" : 300
      }, {
        "height" : 64,
        "url" : "https://i.scdn.co/image/ab67616d000048516c619c39c853f8b1d67b7859",
        "width" : 64
      } ],
      "name" : "Harry Styles",
      "release_date" : "2017-05-12",
      "release_date_precision" : "day",
      "total_tracks" : 10,
      "type" : "album",
      "uri" : "spotify:album:1FZKIm3JVDCxTchXDo5jOV"
    },
    "artists" : [ {
      "external_urls" : {
        "spotify" : "https://open.spotify.com/artist/6KImCVD70vtIoJWnq6nGn3"
      },
      "href" : "https://api.spotify.com/v1/artists/6KImCVD70vtIoJWnq6nGn3",
      "id" : "6KImCVD70vtIoJWnq6nGn3",
      "name" : "Harry Styles",
      "type" : "artist",
      "uri" : "spotify:artist:6KImCVD70vtIoJWnq6nGn3"
    } ],
    "disc_number" : 1,
    "duration_ms" : 224866,
    "explicit" : false,
    "external_ids" : {
      "isrc" : "USSM11703956"
    },
    "external_urls" : {
      "spotify" : "https://open.spotify.com/track/5kRPPEWFJIMox5qIkQkiz5"
    },
    "href" : "https://api.spotify.com/v1/tracks/5kRPPEWFJIMox5qIkQkiz5",
    "id" : "5kRPPEWFJIMox5qIkQkiz5",
    "is_local" : false,
    "is_playable" : true,
    "name" : "Sweet Creature",
    "popularity" : 79,
    "preview_url" : "https://p.scdn.co/mp3-preview/c6545e608f8a8790f65edb274e92bdc6d4b133d5?cid=be7bf93d831d42e2b9e239d3fc1f8a8e",
    "track_number" : 5,
    "type" : "track",
    "uri" : "spotify:track:5kRPPEWFJIMox5qIkQkiz5"
  }, {
    "album" : {
      "album_type" : "album",
      "artists" : [ {
        "external_urls" : {
          "spotify" : "https://open.spotify.com/artist/6KImCVD70vtIoJWnq6nGn3"
        },
        "href" : "https://api.spotify.com/v1/artists/6KImCVD70vtIoJWnq6nGn3",
        "id" : "6KImCVD70vtIoJWnq6nGn3",
        "name" : "Harry Styles",
        "type" : "artist",
        "uri" : "spotify:artist:6KImCVD70vtIoJWnq6nGn3"
      } ],
      "external_urls" : {
        "spotify" : "https://open.spotify.com/album/7xV2TzoaVc0ycW7fwBwAml"
      },
      "href" : "https://api.spotify.com/v1/albums/7xV2TzoaVc0ycW7fwBwAml",
      "id" : "7xV2TzoaVc0ycW7fwBwAml",
      "images" : [ {
        "height" : 640,
        "url" : "https://i.scdn.co/image/ab67616d0000b27377fdcfda6535601aff081b6a",
        "width" : 640
      }, {
        "height" : 300,
        "url" : "https://i.scdn.co/image/ab67616d00001e0277fdcfda6535601aff081b6a",
        "width" : 300
      }, {
        "height" : 64,
        "url" : "https://i.scdn.co/image/ab67616d0000485177fdcfda6535601aff081b6a",
        "width" : 64
      } ],
      "name" : "Fine Line",
      "release_date" : "2019-12-13",
      "release_date_precision" : "day",
      "total_tracks" : 12,
      "type" : "album",
      "uri" : "spotify:album:7xV2TzoaVc0ycW7fwBwAml"
    },
    "artists" : [ {
      "external_urls" : {
        "spotify" : "https://open.spotify.com/artist/6KImCVD70vtIoJWnq6nGn3"
      },
      "href" : "https://api.spotify.com/v1/artists/6KImCVD70vtIoJWnq6nGn3",
      "id" : "6KImCVD70vtIoJWnq6nGn3",
      "name" : "Harry Styles",
      "type" : "artist",
      "uri" : "spotify:artist:6KImCVD70vtIoJWnq6nGn3"
    } ],
    "disc_number" : 1,
    "duration_ms" : 259186,
    "explicit" : false,
    "external_ids" : {
      "isrc" : "USSM11912589"
    },
    "external_urls" : {
      "spotify" : "https://open.spotify.com/track/2IOFZdYYkFxEHVz1w34PoL"
    },
    "href" : "https://api.spotify.com/v1/tracks/2IOFZdYYkFxEHVz1w34PoL",
    "id" : "2IOFZdYYkFxEHVz1w34PoL",
    "is_local" : false,
    "is_playable" : true,
    "name" : "Cherry",
    "popularity" : 79,
    "preview_url" : "https://p.scdn.co/mp3-preview/f8318c0ce76290b873992163473b33454ffb1bc4?cid=be7bf93d831d42e2b9e239d3fc1f8a8e",
    "track_number" : 5,
    "type" : "track",
    "uri" : "spotify:track:2IOFZdYYkFxEHVz1w34PoL"
  }, {
    "album" : {
      "album_type" : "album",
      "artists" : [ {
        "external_urls" : {
          "spotify" : "https://open.spotify.com/artist/6KImCVD70vtIoJWnq6nGn3"
        },
        "href" : "https://api.spotify.com/v1/artists/6KImCVD70vtIoJWnq6nGn3",
        "id" : "6KImCVD70vtIoJWnq6nGn3",
        "name" : "Harry Styles",
        "type" : "artist",
        "uri" : "spotify:artist:6KImCVD70vtIoJWnq6nGn3"
      } ],
      "external_urls" : {
        "spotify" : "https://open.spotify.com/album/1FZKIm3JVDCxTchXDo5jOV"
      },
      "href" : "https://api.spotify.com/v1/albums/1FZKIm3JVDCxTchXDo5jOV",
      "id" : "1FZKIm3JVDCxTchXDo5jOV",
      "images" : [ {
        "height" : 640,
        "url" : "https://i.scdn.co/image/ab67616d0000b2736c619c39c853f8b1d67b7859",
        "width" : 640
      }, {
        "height" : 300,
        "url" : "https://i.scdn.co/image/ab67616d00001e026c619c39c853f8b1d67b7859",
        "width" : 300
      }, {
        "height" : 64,
        "url" : "https://i.scdn.co/image/ab67616d000048516c619c39c853f8b1d67b7859",
        "width" : 64
      } ],
      "name" : "Harry Styles",
      "release_date" : "2017-05-12",
      "release_date_precision" : "day",
      "total_tracks" : 10,
      "type" : "album",
      "uri" : "spotify:album:1FZKIm3JVDCxTchXDo5jOV"
    },
    "artists" : [ {
      "external_urls" : {
        "spotify" : "https://open.spotify.com/artist/6KImCVD70vtIoJWnq6nGn3"
      },
      "href" : "https://api.spotify.com/v1/artists/6KImCVD70vtIoJWnq6nGn3",
      "id" : "6KImCVD70vtIoJWnq6nGn3",
      "name" : "Harry Styles",
      "type" : "artist",
      "uri" : "spotify:artist:6KImCVD70vtIoJWnq6nGn3"
    } ],
    "disc_number" : 1,
    "duration_ms" : 176386,
    "explicit" : false,
    "external_ids" : {
      "isrc" : "USSM11703958"
    },
    "external_urls" : {
      "spotify" : "https://open.spotify.com/track/33SNO8AaciGbNaQFkxvPrW"
    },
    "href" : "https://api.spotify.com/v1/tracks/33SNO8AaciGbNaQFkxvPrW",
    "id" : "33SNO8AaciGbNaQFkxvPrW",
    "is_local" : false,
    "is_playable" : true,
    "name" : "Kiwi",
    "popularity" : 79,
    "preview_url" : "https://p.scdn.co/mp3-preview/1099b77c35ee3f5e08c976077b8ff8059a42f269?cid=be7bf93d831d42e2b9e239d3fc1f8a8e",
    "track_number" : 7,
    "type" : "track",
    "uri" : "spotify:track:33SNO8AaciGbNaQFkxvPrW"
  }, {
    "album" : {
      "album_type" : "album",
      "artists" : [ {
        "external_urls" : {
          "spotify" : "https://open.spotify.com/artist/6KImCVD70vtIoJWnq6nGn3"
        },
        "href" : "https://api.spotify.com/v1/artists/6KImCVD70vtIoJWnq6nGn3",
        "id" : "6KImCVD70vtIoJWnq6nGn3",
        "name" : "Harry Styles",
        "type" : "artist",
        "uri" : "spotify:artist:6KImCVD70vtIoJWnq6nGn3"
      } ],
      "external_urls" : {
        "spotify" : "https://open.spotify.com/album/7xV2TzoaVc0ycW7fwBwAml"
      },
      "href" : "https://api.spotify.com/v1/albums/7xV2TzoaVc0ycW7fwBwAml",
      "id" : "7xV2TzoaVc0ycW7fwBwAml",
      "images" : [ {
        "height" : 640,
        "url" : "https://i.scdn.co/image/ab67616d0000b27377fdcfda6535601aff081b6a",
        "width" : 640
      }, {
        "height" : 300,
        "url" : "https://i.scdn.co/image/ab67616d00001e0277fdcfda6535601aff081b6a",
        "width" : 300
      }, {
        "height" : 64,
        "url" : "https://i.scdn.co/image/ab67616d0000485177fdcfda6535601aff081b6a",
        "width" : 64
      } ],
      "name" : "Fine Line",
      "release_date" : "2019-12-13",
      "release_date_precision" : "day",
      "total_tracks" : 12,
      "type" : "album",
      "uri" : "spotify:album:7xV2TzoaVc0ycW7fwBwAml"
    },
    "artists" : [ {
      "external_urls" : {
        "spotify" : "https://open.spotify.com/artist/6KImCVD70vtIoJWnq6nGn3"
      },
      "href" : "https://api.spotify.com/v1/artists/6KImCVD70vtIoJWnq6nGn3",
      "id" : "6KImCVD70vtIoJWnq6nGn3",
      "name" : "Harry Styles",
      "type" : "artist",
      "uri" : "spotify:artist:6KImCVD70vtIoJWnq6nGn3"
    } ],
    "disc_number" : 1,
    "duration_ms" : 362653,
    "explicit" : false,
    "external_ids" : {
      "isrc" : "USSM11912592"
    },
    "external_urls" : {
      "spotify" : "https://open.spotify.com/track/6SQLk9HSNketfgs2AyIiMs"
    },
    "href" : "https://api.spotify.com/v1/tracks/6SQLk9HSNketfgs2AyIiMs",
    "id" : "6SQLk9HSNketfgs2AyIiMs",
    "is_local" : false,
    "is_playable" : true,
    "name" : "She",
    "popularity" : 78,
    "preview_url" : "https://p.scdn.co/mp3-preview/c09d0c910ed3f8de74a4b6774c78e9f57082de8b?cid=be7bf93d831d42e2b9e239d3fc1f8a8e",
    "track_number" : 8,
    "type" : "track",
    "uri" : "spotify:track:6SQLk9HSNketfgs2AyIiMs"
  } ]
}